neo4jvis/__init__.py
neo4jvis/model/__init__.py
neo4jvis/model/color.py
neo4jvis/model/styled_edge.py
neo4jvis/model/styled_graph.py
neo4jvis/model/styled_node.py
neo4jvis/template/__init__.py
neo4jvis/template/style.css
neo4jvis/template/template.html
neo4jvis/utils/__init__.py
neo4jvis/utils/draw_utils.py
neo4jvis/utils/neomodel_utils.py
neo4jvis/utils/query_utils.py
neo4jvis/utils/validation.py
neo4jvis-0.0.1.dist-info/METADATA
neo4jvis-0.0.1.dist-info/WHEEL
neo4jvis-0.0.1.dist-info/top_level.txt
neo4jvis-0.0.1.dist-info/RECORD
