Metadata-Version: 2.1
Name: neo4jvis
Version: 0.0.1
Summary: Draw neo4j graphs with vis.js
Home-page: UNKNOWN
Author: Author
License: GNU General Public License v3 or later (GPLv3+)
Platform: UNKNOWN
Classifier: Programming Language :: Python :: 3
Classifier: License :: OSI Approved :: GNU General Public License v3 or later (GPLv3+)
Classifier: Operating System :: OS Independent
Requires-Dist: neo4j
Requires-Dist: Jinja2
Requires-Dist: setuptools
Requires-Dist: neomodel
